LICENSE
pre_commit_poetry_export/__init__.py
pre_commit_poetry_export/poetry_export.py
pre_commit_poetry_export-0.1.2.dist-info/entry_points.txt
pre_commit_poetry_export-0.1.2.dist-info/LICENSE
pre_commit_poetry_export-0.1.2.dist-info/WHEEL
pre_commit_poetry_export-0.1.2.dist-info/METADATA
pre_commit_poetry_export-0.1.2.dist-info/RECORD
